{"metadata": {"Header 1": "Afholdelse af ferie", "Header 2": "Reduktion af den ferieberettigede løn", "Header 3": "Timelønnede ferie med løn, reduceres i den ferieberettiget løn", "url": "https://help.vismaenterprise.dk/vismaloen-standard/ferie/76-afholdelse-af-ferie"}, "content": "### Timelønnede ferie med løn, reduceres i den ferieberettiget løn\nTimelønnede der er ansat med ret til ferie med løn, skal reduceres i den ferieberettigede løn, når de afholder ferie. Dette kræver at fraværsrækkefølge benyttes (fraværslønart 3950 skal oprettes på fraværskoden), samt at resultattabel:  \nDAGTIM er udfyldt med 1 på relevante løngrupper"}