{"metadata": {"Header 1": "Aftalefri", "Header 2": "Udbetaling af aftalefridage/-timer, som en variabel lønoplysning", "url": "https://help.vismaenterprise.dk/vismaloen-standard/medarbejdertilgode/1-aftalefri"}, "content": "## Udbetaling af aftalefridage/-timer, som en variabel lønoplysning\nDu kan udbetale aftalefri som en variabel lønoplysning, hvor der ikke sker en registrering i fraværssystemet.\nDu kan bruge følgende variable lønarter til udbetaling af aftalefri:  \nLønart 3410 - Udbetaling af aftalefridageTømmer saldoen og udbetaler aftalefridagene i timer ud fra formlen 4% af månedslønnen divideret med 7,4 gange antal timer\nLønart 3411 - Udbetaling af aftalefridage i timerTømmer saldoen og udbetaler dagene * med 7,4 time, som ganges med månedsløn divideret med normtid overenskomst gange med normtid medarbejder pr. Time.\nLønart 3412 – Udbetaling af aftalefritimerOprettes med antal timer der ønskes udbetalt og så hentes satsen automatisk fra medarbejderens personlige satser eller fra resultattabel 1100\nLønart 3415 - Udbetaling af aftalefritimerDu angiver timerne og satsen, som ganges med hinanden og udbetales\nLønart 3416 – Udbetaling af aftalefritimerOprettes med et antal og en sats. Lønarten tæller med i ATP timerne og nedskriver saldoen på aftalefritimer\nLønart 3417 – Udbetaling af aftalefridage i timerOprettes med antal aftalefritimer og lønarten bruger månedslønnen divideret med normtiden som timeløn og saldoen på aftalefritimer nedskrives med antal timer\nLønart 3418 – Udbetaling af aftalefritimerOprettes med antal timer som skal udbetales og ganges med satsen fra resultattabel 3418."}