{"metadata": {"Header 1": "Feriefridage", "Header 2": "Afstemning af feriefrisaldi", "url": "https://help.vismaenterprise.dk/vismaloen-standard/ferie/10-feriefridage"}, "content": "## Afstemning af feriefrisaldi\nRapporten ’Medarbejder til gode (år til dato)’ viser ’år til dato’ saldi for\n* Feriefridage  \nRapporten er sorteret efter Arbejdsgiver / Afdeling / Medarbejdernummer. Rapporten er som udgangspunkt en csv-fil, men kan også udskrives som en HTML liste. Du kan vælge denne filtype ved dannelsen af rapporten ved at vælge ’Nej’ til Datafil-output.  \nRapporten/filen kan rekvireres på følgende måder:\nI lønkørslen\nHvis rapporten/filen ønskes dannet ved hver lønkørsel, skal du sætte rapporten op på følgende måde:  \nGå til Arbejdsgiver → Arbejdsgiver stamoplysninger\nVælg Rapportbestilling i højremenuen\nVælg rapporten ’Medarbejder til gode (år til dato)’\nDobbeltklik på linjen\nSkriv en startdato\nKlik på OK  \nRapporten dannes både som liste og som csv-fil i lønkørslen.  \nVed bestilling ad hoc\nDu kan danne rapporten på følgende måde:  \nGå til Rapporter → Rapporter\nVælg Medarbejder til gode (år til dato) i højremenuen  \nHer får du mulighed for at bestille rapporten som liste eller som en csv-fil. Rapporten/filen rekvireres pr. kørselsordre."}