{"metadata": {"Header 1": "Søgne- og Helligdage (SH)", "Header 2": "Overførsel af SH-saldo til nyt kalenderår", "url": "https://help.vismaenterprise.dk/vismaloen-standard/medarbejdertilgode/65-sogne-og-helligdage"}, "content": "## Overførsel af SH-saldo til nyt kalenderår\nFølgende lønart kan bruges, hvis saldoen skal overføres fra sidste år:  \nLønart 450 - Søgne-/Helligdage (SH)  \nOvenstående lønart skal i felter ’SH-Saldo overføres ja=1/nej=0 udfyldes med 1’, hvis saldoen ønskes overført, og med 0 hvis en saldo ikke skal overføres.\nHar du beskattet SH portioner indeværende år, som skal overføres til nyt kalenderår, skal det ske med lønart 4530. Husk at du udbetaler portionerne i den første lønkørsel i det nye år.\nUdbetalingen sker med variabel lønart  \nLønart 4560 - Netto SH fra sidste år"}