{"metadata": {"Header 1": "Decentral registrering", "Header 2": "Indlæsning af fil til Visma Løn", "url": "https://help.vismaenterprise.dk/vismaloen-standard/decantral-registrering/86-decentral-registrering"}, "content": "## Indlæsning af fil til Visma Løn\nArbejdsgiver skal være tilmeldt ’Serviceydelse 7’ for at kunne foretage indlæsning af filer.\nSådan indlæses filen i Visma Løn:  \nGå til Lønadministration → Overførsel → Decentral registrering\nIndlæs filen, klik på Indlæs\nFind filen, klik på OK\nHerefter startes et job, som vises under Vis job. Når jobbet er sluttet, klik på Hent aktuel\nKlik herefter på Åbn\nDobbeltklik på filen, der vises og herefter klik på Åbn\nPå skærmen vises Kvittering for decentral registrering. Rapporten viser, hvor mange linjer, der er henholdsvis Modtaget, Indlæst og Afvist. De linjer, der er modtaget og indlæst, findes under de respektive skærmbilleder i lønsystemet.De linjer, der er afvist, vil blive vist på rapporten Kvittering for decentral registrering, hvoraf medarbejdernr., og fejl/årsagen for de afviste linjer vil fremgå.  \n👩‍🏫 Eksempel:\nHer ses opbygningen af en csv-fil med alle formater og adskillelsestegn er ’;’ (semikolon):\n18;1;MLE-05-AFDE;300;HR\n18;1;MLE-10-UDBE;Kbh;København\n18;;MLE-15-REST;1100;01082008;;;T3;;;120;60\n18;;MLE-15-REST;1100;01082008;;;F3;165\n18;;MLE-15-REST;1100;01082008;;;F4;;175\n18;1;MLE-25-MEDA;3;3001609992;;Jensen;Gurli;Skogen 12;SE-45678 Malmø;0;;01082008;[gj@hotmail.dk](mailto:gj@hotmail.dk);SE;000100;H;01082008\n18;1;MLE-25-MEDA;4;2602639991;;Olsen;Thomas;Sorte vænget 22;;2750;;15082008;;;000015;B;15082008\n18;1;MLE-27-HRME;3;3001609992;;Jensen;Gurli;Skogen 12;;SE-45678; Malmø;01082008;[gj@hotmail.dk](mailto:gj@hotmail.dk);SE;000100;H;01082008\n18;1;MLE-27-HRME;4;2602639991;;Olsen;Thomas;Sorte vænget 22;;2750;;15082008;;;000015;B;15082008\n18;1;MLE-30-ANSF;3;01082008;;;;1001;HR konsulent;130.00;;F1;300;;;1010244230\n18;1;MLE-30-ANSF;4;15082008;;;;3001;Lager;0;;T1;100;Kbh;;1010244230\n18;1;MLE-30-ANSF;10086;01082008;;3;31082008\n18;1;MLE-32-HRAN;3;01082008;;;;1001;HR konsulent;130.00;;F1;300;;;1010244230\n18;1;MLE-32-HRAN;4;15082008;;;;3001;Lager;0;;T1;100;Kbh;;1010244230\n18;1;MLE-32-HRAN;10086;01082008;;3;31082008\n18;1;MLE-35-REGK;3;01082009;;1234;9481247\n18;1;MLE-35-REGK;4;15082008;;1222;3185784375\n18;1;MLE-40-LONA;3;01082008;;9900;;;;20000\n18;1;MLE-40-LONA;3;01082008;;6200;;;;;5;;;10;;;;;;;2003\n18;1;MLE-40-LONA;3;01082008;;9011;;120\n18;1;MLE-40-LONA;3;01082008;;1303;;5;120\n18;1;MLE-40-LONA;3;01082008;;3000;;;;6500\n18;1;MLE-40-LONA;3;01082008;31122008;3010\n18;1;MLE-40-LONA;4;15082008;;6003;;;;;3.7;;;7.4;2;;;;;;2115;;;;1\n18;1;MLE-40-LONA;4;15082008;;6410;;;;500;;;;;;;;;2345;6544533\n18;1;MLE-40-LONA;4;15082008;;1100;;165\n18;1;MLE-40-LONA;4;15082008;;9905;;;;170\n18;1;MLE-40-LONA;4;15082008;;9906;;;;15\n18;1;MLE-45-ERIN;3;01082008;1;Jubilæum 2018\n18;1;MLE-50-ANSO;3;300;412110;;01082008\n18;1;MLE-50-ANSO;3;800;4;;01082008\n18;1;MLE-50-ANSO;3;600;99999;30.00;01082008\n18;1;MLE-55-FRAV;10078;12082008;13082008;40;Ferie i august;2\n18;1;MLE-55-FRAV;987;14082008;14082008;18;Dagpenge;7.5;125\n18;1;MLE-55-FRAV;992;02012008;02012008;40;;;;9\n18;1;MLE-60-EIND;3;11;0;01082008\n18;1;MLE-60-EIND;4;66;0;15082008;;5000\n18;1;MLE-65-GREK;1;01082008;H\n18;1;MLE-80-TLF;1;12345678;;Mobiltelefon"}