{"metadata": {"Header 1": "Bogf\u00f8ring - ferie", "Header 2": "Hens\u00e6ttelse af ferie - regnskabslovens konkrete metode", "Header 3": "Hens\u00e6ttelse af feriepenge efter regnskabslovens konkrete metode", "url": "https://help.vismaenterprise.dk/vismaloen-standard/ferie/85-bogforing-ferie"}, "content": "### Hens\u00e6ttelse af feriepenge efter regnskabslovens konkrete metode\nEfter ny ferielov er indf\u00f8rt er der kommet en regnskabsm\u00e6ssig konsekvens og en ny mulighed for hens\u00e6ttelse af feriepenge i Visma L\u00f8n. Det betyder at du kan hens\u00e6tte efter den konkrete/faktiske metode. Denne metode omfatter kun de medarbejdere som har ferie med l\u00f8n.\nGrundlag: AM-grundlag (felt 13) + pension arbejdsgiver (felt 148) + ATP (felt 46) + pension l\u00f8nmodtager felt 147 -/+ l\u00f8nartstype 7500 (i denne l\u00f8nartstype er oprettet l\u00f8narterne for Bonus, som er variable med\u00a0et minus)\nSummen af grundlaget divideres med medarbejderens normtid for at finde timel\u00f8nnen.\nFerie i dage:Derefter skal der udregnes en dagssats ved at sige timel\u00f8nnen gange med 7,4 gange med (medarbejder normtid/160,33)Denne dagssats skal s\u00e5 ganges med antallet af restferiedage.P\u00e5 stillingskategorien oprettes f\u00f8lgende stillingskategoril\u00f8nart:L\u00f8nart&nbsp;19883 - Hens\u00e6tter dageP\u00e5 kontoplanen oprettes i debet p\u00e5 resultatopg\u00f8relsen og i kredit p\u00e5 balancen f\u00f8lgende l\u00f8narter:L\u00f8nart&nbsp;19883 - Ny ferielov&nbsp;dage hens\u00e6ttelse&nbsp;Ferie i timer:Timel\u00f8nnen skal s\u00e5 ganges med antallet af rest ferietimer.M\u00e5neden efter skal der g\u00f8res det samme, men her kigges der p\u00e5 hvad der blev hensat sidste m\u00e5ned og s\u00e5 er det differencen som skal bogf\u00f8res.&nbsp;P\u00e5 stillingskategorien oprettes f\u00f8lgende stillingskategoril\u00f8nart:L\u00f8nart&nbsp;19884&nbsp;- Hens\u00e6tter timerP\u00e5 kontoplanen oprettes i debet p\u00e5 resultatopg\u00f8relsen og i kredit p\u00e5 balancen f\u00f8lgende l\u00f8narter:L\u00f8nart&nbsp;19884&nbsp;- Ny ferielov&nbsp;timer hens\u00e6ttelse\u26a0\ufe0f OBS: &nbsp;Der kan ikke foretages omk\u00f8rsel af bogf\u00f8ring p\u00e5 den konkrete metode.Anvendes denne metode til hens\u00e6ttelse skal f\u00f8lgende l\u00f8narter ikke optr\u00e6de i den kontoplan:L\u00f8nart 44960, 44961, 44962, 44963, 44964, 44966 og 44968."}