{"metadata": {"Header 1": "Overførsel, udbetaling og nulstilling af restferie", "Header 2": "Eksempler på behandling af restferiedage/timer", "Header 3": "Scenarie 3: Funktionær deltid - udbetales", "url": "https://help.vismaenterprise.dk/vismaloen-standard/ferie/87-overforsel-udbetaling-og-nulstilling-af-restferie"}, "content": "### Scenarie 3: Funktionær deltid - udbetales\nMedarbejder arbejder 3 dage om ugen, og optjener 15 feriedage pr. år jf. opsætning på lønart 9980.\nMedarbejder har 3 feriedage tilbage, men skal have 5 dage udbetalt.\nSådan gør du\nLønart 40105 - korrektion af 2 dage.Lønart 4760 - udbetaling af 5 dage.\n⚠️ OBS: Omregnes medarbejders feriedage på lønart 9980 &#39;Omregning feriedage v. deltid&#39;, og skal der udbetales 5. Ferieuge, er det ved udbetaling nødvendigt at opskrive dagene til korrekte enheder for en fuldtidsansat inden udbetalingen."}